pySFeel/SFeel.py
pySFeel/__init__.py
pySFeel-1.4.2.dist-info/LICENSE
pySFeel-1.4.2.dist-info/METADATA
pySFeel-1.4.2.dist-info/WHEEL
pySFeel-1.4.2.dist-info/top_level.txt
pySFeel-1.4.2.dist-info/RECORD
