Metadata-Version: 2.1
Name: pySFeel
Version: 1.4.2
Summary: An implementation of S-FEEL using SLY (lex and yacc for Python3)
Home-page: https://github.com/russellmcdonell/pySFeel
Author: Russell McDonell
Author-email: russell.mcdonell@c-cost.com
Classifier: Programming Language :: Python :: 3
Classifier: License :: OSI Approved :: GNU General Public License v3 (GPLv3)
Classifier: Operating System :: OS Independent
Requires-Python: >=3.6
License-File: LICENSE
Requires-Dist: sly
Requires-Dist: datetime
Requires-Dist: python-dateutil
Requires-Dist: statistics
